ory_keto_client/__init__.py
ory_keto_client/api_client.py
ory_keto_client/configuration.py
ory_keto_client/exceptions.py
ory_keto_client/model_utils.py
ory_keto_client/rest.py
ory_keto_client/api/__init__.py
ory_keto_client/api/metadata_api.py
ory_keto_client/api/read_api.py
ory_keto_client/api/write_api.py
ory_keto_client/apis/__init__.py
ory_keto_client/model/__init__.py
ory_keto_client/model/expand_tree.py
ory_keto_client/model/generic_error.py
ory_keto_client/model/get_check_response.py
ory_keto_client/model/get_relation_tuples_response.py
ory_keto_client/model/get_version200_response.py
ory_keto_client/model/health_not_ready_status.py
ory_keto_client/model/health_status.py
ory_keto_client/model/internal_relation_tuple.py
ory_keto_client/model/is_alive200_response.py
ory_keto_client/model/is_ready503_response.py
ory_keto_client/model/patch_delta.py
ory_keto_client/model/relation_query.py
ory_keto_client/model/relation_tuple.py
ory_keto_client/model/subject_set.py
ory_keto_client/model/version.py
ory_keto_client/models/__init__.py
forestvpn_ory_keto_client-0.9.0a0.dist-info/LICENSE
forestvpn_ory_keto_client-0.9.0a0.dist-info/METADATA
forestvpn_ory_keto_client-0.9.0a0.dist-info/WHEEL
forestvpn_ory_keto_client-0.9.0a0.dist-info/top_level.txt
forestvpn_ory_keto_client-0.9.0a0.dist-info/RECORD
