Metadata-Version: 2.1
Name: forestvpn-ory-keto-client
Version: 0.9.0a0
Summary: Ory Keto API
Home-page: https://github.com/forestvpn/ory-keto-client-python
Author: OpenAPI Generator community
Author-email: hi@ory.sh
License: Apache 2.0
Keywords: OpenAPI,OpenAPI-Generator,Ory Keto API
Requires-Python: >=3.6
License-File: LICENSE
Requires-Dist: urllib3 (>=1.25.3)
Requires-Dist: python-dateutil
